hiro_graph_client/VERSION
hiro_graph_client/__init__.py
hiro_graph_client/actionwebsocket.py
hiro_graph_client/appclient.py
hiro_graph_client/authclient.py
hiro_graph_client/authzclient.py
hiro_graph_client/client.py
hiro_graph_client/clientlib.py
hiro_graph_client/eventswebsocket.py
hiro_graph_client/iamclient.py
hiro_graph_client/kiclient.py
hiro_graph_client/variablesclient.py
hiro_graph_client/version.py
hiro_graph_client/websocketlib.py
hiro_graph_client-5.3.3.dist-info/METADATA
hiro_graph_client-5.3.3.dist-info/WHEEL
hiro_graph_client-5.3.3.dist-info/top_level.txt
hiro_graph_client-5.3.3.dist-info/RECORD
