Metadata-Version: 2.4
Name: hiro_graph_client
Version: 5.3.3
Summary: Hiro Client for Graph REST API of HIRO 7
Home-page: https://github.com/arago/hiro-client-python
Author: arago GmbH
Author-email: info@arago.co
Maintainer: Wolfgang Hübner
License: MIT
Project-URL: GitHub, https://github.com/arago/hiro-client-python
Project-URL: Documentation, https://github.com/arago/hiro-client-python/blob/master/src/README.md
Project-URL: Changelog, https://github.com/arago/hiro-client-python/blob/master/CHANGELOG.md
Keywords: arago HIRO7 API REST WebSocket
Classifier: Programming Language :: Python :: 3
Classifier: Programming Language :: Python :: 3.7
Classifier: License :: OSI Approved :: MIT License
Classifier: Operating System :: OS Independent
Classifier: Intended Audience :: Developers
Classifier: Topic :: Software Development :: Libraries
Requires-Python: >=3.7
Requires-Dist: wheel
Requires-Dist: requests
Requires-Dist: backoff
Requires-Dist: websocket-client
Requires-Dist: apscheduler
Provides-Extra: doc
Requires-Dist: sphinx; extra == "doc"
Requires-Dist: sphinx-rtd-theme; extra == "doc"
Dynamic: author
Dynamic: author-email
Dynamic: classifier
Dynamic: description
Dynamic: description-content-type
Dynamic: home-page
Dynamic: keywords
Dynamic: license
Dynamic: maintainer
Dynamic: project-url
Dynamic: provides-extra
Dynamic: requires-dist
Dynamic: requires-python
Dynamic: summary
